main.py
csv_from_mbox-0.4.5.dist-info/entry_points.txt
csv_from_mbox-0.4.5.dist-info/LICENSE.md
csv_from_mbox-0.4.5.dist-info/WHEEL
csv_from_mbox-0.4.5.dist-info/METADATA
csv_from_mbox-0.4.5.dist-info/RECORD
