Metadata-Version: 2.1
Name: csv-from-mbox
Version: 0.4.5
Summary: Python script for extracting emails contained in the 'from' field of your mailbox from an .mbox file.
Home-page: https://github.com/vsevolod-mineev/csv-from-mbox
License: MIT
Author: Vsevolod Mineev
Author-email: vsevolod.mineev@gmail.com
Requires-Python: >=3.9,<4.0
Classifier: License :: OSI Approved :: MIT License
Classifier: Programming Language :: Python :: 3
Classifier: Programming Language :: Python :: 3.10
Classifier: Programming Language :: Python :: 3.9
Project-URL: Documentation, https://github.com/vsevolod-mineev/csv-from-mbox
Project-URL: Repository, https://github.com/vsevolod-mineev/csv-from-mbox
